{
  "expo": {
    "name": "she-shield",
    "slug": "she-shield",
    "version": "1.0.0",
    "orientation": "portrait",
    "icon": "./assets/icon.png",
    "userInterfaceStyle": "light",
    "newArchEnabled": true,
    "splash": {
      "backgroundColor": "#3D212B"
    },
    "assetBundlePatterns": [
      "**/*"
    ],
    "android": {
      "adaptiveIcon": {
        "foregroundImage": "./assets/adaptive-icon.png",
        "backgroundColor": "#ffffff"
      },
      "package": "com.sheshield.app",
      "googleServicesFile": "./google-services.json"
    },
    "web": {
      "favicon": "./assets/favicon.png"
    },
    "scheme": "sheshield",
    "extra": {
      "eas": {
        "projectId": "686962153219"
      }
    }
  }
}
